README.md
setup.py
GraphCVAE/GraphCVAE.py
GraphCVAE/__init__.py
GraphCVAE/_compat.py
GraphCVAE/adj.py
GraphCVAE/augment.py
GraphCVAE/his_feat.py
GraphCVAE/model.py
GraphCVAE/preprocess.py
GraphCVAE/utils.py
GraphCVAE/utils_func.py
GraphCVAE.egg-info/PKG-INFO
GraphCVAE.egg-info/SOURCES.txt
GraphCVAE.egg-info/dependency_links.txt
GraphCVAE.egg-info/not-zip-safe
GraphCVAE.egg-info/requires.txt
GraphCVAE.egg-info/top_level.txt