Metadata-Version: 2.1
Name: GraphCVAE
Version: 1.0.3
Summary: GraphCVAE: Uncovering Cell Heterogeneity and Therapeutic Target Discovery through Residual and Contrastive Learning
Home-page: https://github.com/ZhiWeiZhang0336/GraphCVAE
Author: Zhiwei Zhang
Author-email: 2023520218@bipt.eud.cn
License: MIT
